zhiweimorgenexamplehahaha/__init__.py
zhiweimorgenexamplehahaha/morgen_example_zhangZhiwei.py
zhiweimorgenexamplehahaha-0.0.0.dist-info/LICENSE
zhiweimorgenexamplehahaha-0.0.0.dist-info/METADATA
zhiweimorgenexamplehahaha-0.0.0.dist-info/WHEEL
zhiweimorgenexamplehahaha-0.0.0.dist-info/top_level.txt
zhiweimorgenexamplehahaha-0.0.0.dist-info/RECORD
